{
  "type": "File",
  "start": 0,
  "end": 311,
  "loc": {
    "start": {
      "line": 1,
      "column": 0
    },
    "end": {
      "line": 11,
      "column": 0
    }
  },
  "program": {
    "type": "Program",
    "start": 0,
    "end": 311,
    "loc": {
      "start": {
        "line": 1,
        "column": 0
      },
      "end": {
        "line": 11,
        "column": 0
      }
    },
    "sourceType": "module",
    "body": [
      {
        "type": "VariableDeclaration",
        "start": 0,
        "end": 44,
        "loc": {
          "start": {
            "line": 1,
            "column": 0
          },
          "end": {
            "line": 1,
            "column": 44
          }
        },
        "declarations": [
          {
            "type": "VariableDeclarator",
            "start": 6,
            "end": 43,
            "loc": {
              "start": {
                "line": 1,
                "column": 6
              },
              "end": {
                "line": 1,
                "column": 43
              }
            },
            "id": {
              "type": "Identifier",
              "start": 6,
              "end": 15,
              "loc": {
                "start": {
                  "line": 1,
                  "column": 6
                },
                "end": {
                  "line": 1,
                  "column": 15
                },
                "identifierName": "broadcast"
              },
              "name": "broadcast"
            },
            "init": {
              "type": "CallExpression",
              "start": 18,
              "end": 43,
              "loc": {
                "start": {
                  "line": 1,
                  "column": 18
                },
                "end": {
                  "line": 1,
                  "column": 43
                }
              },
              "callee": {
                "type": "Identifier",
                "start": 18,
                "end": 25,
                "loc": {
                  "start": {
                    "line": 1,
                    "column": 18
                  },
                  "end": {
                    "line": 1,
                    "column": 25
                  },
                  "identifierName": "require"
                },
                "name": "require"
              },
              "arguments": [
                {
                  "type": "StringLiteral",
                  "start": 26,
                  "end": 42,
                  "loc": {
                    "start": {
                      "line": 1,
                      "column": 26
                    },
                    "end": {
                      "line": 1,
                      "column": 42
                    }
                  },
                  "extra": {
                    "rawValue": "./broadcast.js",
                    "raw": "'./broadcast.js'"
                  },
                  "value": "./broadcast.js"
                }
              ]
            }
          }
        ],
        "kind": "const"
      },
      {
        "type": "VariableDeclaration",
        "start": 45,
        "end": 95,
        "loc": {
          "start": {
            "line": 2,
            "column": 0
          },
          "end": {
            "line": 2,
            "column": 50
          }
        },
        "declarations": [
          {
            "type": "VariableDeclarator",
            "start": 51,
            "end": 94,
            "loc": {
              "start": {
                "line": 2,
                "column": 6
              },
              "end": {
                "line": 2,
                "column": 49
              }
            },
            "id": {
              "type": "Identifier",
              "start": 51,
              "end": 63,
              "loc": {
                "start": {
                  "line": 2,
                  "column": 6
                },
                "end": {
                  "line": 2,
                  "column": 18
                },
                "identifierName": "logPartySize"
              },
              "name": "logPartySize"
            },
            "init": {
              "type": "CallExpression",
              "start": 66,
              "end": 94,
              "loc": {
                "start": {
                  "line": 2,
                  "column": 21
                },
                "end": {
                  "line": 2,
                  "column": 49
                }
              },
              "callee": {
                "type": "Identifier",
                "start": 66,
                "end": 73,
                "loc": {
                  "start": {
                    "line": 2,
                    "column": 21
                  },
                  "end": {
                    "line": 2,
                    "column": 28
                  },
                  "identifierName": "require"
                },
                "name": "require"
              },
              "arguments": [
                {
                  "type": "StringLiteral",
                  "start": 74,
                  "end": 93,
                  "loc": {
                    "start": {
                      "line": 2,
                      "column": 29
                    },
                    "end": {
                      "line": 2,
                      "column": 48
                    }
                  },
                  "extra": {
                    "rawValue": "./logPartySize.js",
                    "raw": "\"./logPartySize.js\""
                  },
                  "value": "./logPartySize.js"
                }
              ]
            }
          }
        ],
        "kind": "const"
      },
      {
        "type": "FunctionDeclaration",
        "start": 97,
        "end": 278,
        "loc": {
          "start": {
            "line": 4,
            "column": 0
          },
          "end": {
            "line": 8,
            "column": 1
          }
        },
        "id": {
          "type": "Identifier",
          "start": 106,
          "end": 118,
          "loc": {
            "start": {
              "line": 4,
              "column": 9
            },
            "end": {
              "line": 4,
              "column": 21
            },
            "identifierName": "removePlayer"
          },
          "name": "removePlayer"
        },
        "generator": false,
        "expression": false,
        "async": false,
        "params": [
          {
            "type": "Identifier",
            "start": 119,
            "end": 130,
            "loc": {
              "start": {
                "line": 4,
                "column": 22
              },
              "end": {
                "line": 4,
                "column": 33
              },
              "identifierName": "connections"
            },
            "name": "connections"
          },
          {
            "type": "Identifier",
            "start": 132,
            "end": 139,
            "loc": {
              "start": {
                "line": 4,
                "column": 35
              },
              "end": {
                "line": 4,
                "column": 42
              },
              "identifierName": "players"
            },
            "name": "players"
          },
          {
            "type": "Identifier",
            "start": 141,
            "end": 149,
            "loc": {
              "start": {
                "line": 4,
                "column": 44
              },
              "end": {
                "line": 4,
                "column": 52
              },
              "identifierName": "playerId"
            },
            "name": "playerId"
          }
        ],
        "body": {
          "type": "BlockStatement",
          "start": 151,
          "end": 278,
          "loc": {
            "start": {
              "line": 4,
              "column": 54
            },
            "end": {
              "line": 8,
              "column": 1
            }
          },
          "body": [
            {
              "type": "ExpressionStatement",
              "start": 157,
              "end": 180,
              "loc": {
                "start": {
                  "line": 5,
                  "column": 4
                },
                "end": {
                  "line": 5,
                  "column": 27
                }
              },
              "expression": {
                "type": "AssignmentExpression",
                "start": 157,
                "end": 179,
                "loc": {
                  "start": {
                    "line": 5,
                    "column": 4
                  },
                  "end": {
                    "line": 5,
                    "column": 26
                  }
                },
                "operator": "=",
                "left": {
                  "type": "MemberExpression",
                  "start": 157,
                  "end": 174,
                  "loc": {
                    "start": {
                      "line": 5,
                      "column": 4
                    },
                    "end": {
                      "line": 5,
                      "column": 21
                    }
                  },
                  "object": {
                    "type": "Identifier",
                    "start": 157,
                    "end": 164,
                    "loc": {
                      "start": {
                        "line": 5,
                        "column": 4
                      },
                      "end": {
                        "line": 5,
                        "column": 11
                      },
                      "identifierName": "players"
                    },
                    "name": "players"
                  },
                  "property": {
                    "type": "Identifier",
                    "start": 165,
                    "end": 173,
                    "loc": {
                      "start": {
                        "line": 5,
                        "column": 12
                      },
                      "end": {
                        "line": 5,
                        "column": 20
                      },
                      "identifierName": "playerId"
                    },
                    "name": "playerId"
                  },
                  "computed": true
                },
                "right": {
                  "type": "ObjectExpression",
                  "start": 177,
                  "end": 179,
                  "loc": {
                    "start": {
                      "line": 5,
                      "column": 24
                    },
                    "end": {
                      "line": 5,
                      "column": 26
                    }
                  },
                  "properties": []
                }
              }
            },
            {
              "type": "ExpressionStatement",
              "start": 185,
              "end": 245,
              "loc": {
                "start": {
                  "line": 6,
                  "column": 4
                },
                "end": {
                  "line": 6,
                  "column": 64
                }
              },
              "expression": {
                "type": "CallExpression",
                "start": 185,
                "end": 244,
                "loc": {
                  "start": {
                    "line": 6,
                    "column": 4
                  },
                  "end": {
                    "line": 6,
                    "column": 63
                  }
                },
                "callee": {
                  "type": "Identifier",
                  "start": 185,
                  "end": 194,
                  "loc": {
                    "start": {
                      "line": 6,
                      "column": 4
                    },
                    "end": {
                      "line": 6,
                      "column": 13
                    },
                    "identifierName": "broadcast"
                  },
                  "name": "broadcast"
                },
                "arguments": [
                  {
                    "type": "Identifier",
                    "start": 195,
                    "end": 206,
                    "loc": {
                      "start": {
                        "line": 6,
                        "column": 14
                      },
                      "end": {
                        "line": 6,
                        "column": 25
                      },
                      "identifierName": "connections"
                    },
                    "name": "connections"
                  },
                  {
                    "type": "ObjectExpression",
                    "start": 208,
                    "end": 243,
                    "loc": {
                      "start": {
                        "line": 6,
                        "column": 27
                      },
                      "end": {
                        "line": 6,
                        "column": 62
                      }
                    },
                    "properties": [
                      {
                        "type": "ObjectProperty",
                        "start": 209,
                        "end": 228,
                        "loc": {
                          "start": {
                            "line": 6,
                            "column": 28
                          },
                          "end": {
                            "line": 6,
                            "column": 47
                          }
                        },
                        "method": false,
                        "shorthand": false,
                        "computed": false,
                        "key": {
                          "type": "Identifier",
                          "start": 209,
                          "end": 213,
                          "loc": {
                            "start": {
                              "line": 6,
                              "column": 28
                            },
                            "end": {
                              "line": 6,
                              "column": 32
                            },
                            "identifierName": "type"
                          },
                          "name": "type"
                        },
                        "value": {
                          "type": "StringLiteral",
                          "start": 215,
                          "end": 228,
                          "loc": {
                            "start": {
                              "line": 6,
                              "column": 34
                            },
                            "end": {
                              "line": 6,
                              "column": 47
                            }
                          },
                          "extra": {
                            "rawValue": "player-left",
                            "raw": "\"player-left\""
                          },
                          "value": "player-left"
                        }
                      },
                      {
                        "type": "ObjectProperty",
                        "start": 230,
                        "end": 242,
                        "loc": {
                          "start": {
                            "line": 6,
                            "column": 49
                          },
                          "end": {
                            "line": 6,
                            "column": 61
                          }
                        },
                        "method": false,
                        "shorthand": false,
                        "computed": false,
                        "key": {
                          "type": "Identifier",
                          "start": 230,
                          "end": 232,
                          "loc": {
                            "start": {
                              "line": 6,
                              "column": 49
                            },
                            "end": {
                              "line": 6,
                              "column": 51
                            },
                            "identifierName": "id"
                          },
                          "name": "id"
                        },
                        "value": {
                          "type": "Identifier",
                          "start": 234,
                          "end": 242,
                          "loc": {
                            "start": {
                              "line": 6,
                              "column": 53
                            },
                            "end": {
                              "line": 6,
                              "column": 61
                            },
                            "identifierName": "playerId"
                          },
                          "name": "playerId"
                        }
                      }
                    ]
                  }
                ]
              }
            },
            {
              "type": "ExpressionStatement",
              "start": 250,
              "end": 276,
              "loc": {
                "start": {
                  "line": 7,
                  "column": 4
                },
                "end": {
                  "line": 7,
                  "column": 30
                }
              },
              "expression": {
                "type": "CallExpression",
                "start": 250,
                "end": 275,
                "loc": {
                  "start": {
                    "line": 7,
                    "column": 4
                  },
                  "end": {
                    "line": 7,
                    "column": 29
                  }
                },
                "callee": {
                  "type": "Identifier",
                  "start": 250,
                  "end": 262,
                  "loc": {
                    "start": {
                      "line": 7,
                      "column": 4
                    },
                    "end": {
                      "line": 7,
                      "column": 16
                    },
                    "identifierName": "logPartySize"
                  },
                  "name": "logPartySize"
                },
                "arguments": [
                  {
                    "type": "Identifier",
                    "start": 263,
                    "end": 274,
                    "loc": {
                      "start": {
                        "line": 7,
                        "column": 17
                      },
                      "end": {
                        "line": 7,
                        "column": 28
                      },
                      "identifierName": "connections"
                    },
                    "name": "connections"
                  }
                ]
              }
            }
          ],
          "directives": []
        }
      },
      {
        "type": "ExpressionStatement",
        "start": 280,
        "end": 310,
        "loc": {
          "start": {
            "line": 10,
            "column": 0
          },
          "end": {
            "line": 10,
            "column": 30
          }
        },
        "expression": {
          "type": "AssignmentExpression",
          "start": 280,
          "end": 309,
          "loc": {
            "start": {
              "line": 10,
              "column": 0
            },
            "end": {
              "line": 10,
              "column": 29
            }
          },
          "operator": "=",
          "left": {
            "type": "MemberExpression",
            "start": 280,
            "end": 294,
            "loc": {
              "start": {
                "line": 10,
                "column": 0
              },
              "end": {
                "line": 10,
                "column": 14
              }
            },
            "object": {
              "type": "Identifier",
              "start": 280,
              "end": 286,
              "loc": {
                "start": {
                  "line": 10,
                  "column": 0
                },
                "end": {
                  "line": 10,
                  "column": 6
                },
                "identifierName": "module"
              },
              "name": "module"
            },
            "property": {
              "type": "Identifier",
              "start": 287,
              "end": 294,
              "loc": {
                "start": {
                  "line": 10,
                  "column": 7
                },
                "end": {
                  "line": 10,
                  "column": 14
                },
                "identifierName": "exports"
              },
              "name": "exports"
            },
            "computed": false
          },
          "right": {
            "type": "Identifier",
            "start": 297,
            "end": 309,
            "loc": {
              "start": {
                "line": 10,
                "column": 17
              },
              "end": {
                "line": 10,
                "column": 29
              },
              "identifierName": "removePlayer"
            },
            "name": "removePlayer"
          }
        }
      }
    ],
    "directives": []
  },
  "comments": [],
  "tokens": [
    {
      "type": {
        "label": "const",
        "keyword": "const",
        "beforeExpr": false,
        "startsExpr": false,
        "rightAssociative": false,
        "isLoop": false,
        "isAssign": false,
        "prefix": false,
        "postfix": false,
        "binop": null,
        "updateContext": null
      },
      "value": "const",
      "start": 0,
      "end": 5,
      "loc": {
        "start": {
          "line": 1,
          "column": 0
        },
        "end": {
          "line": 1,
          "column": 5
        }
      }
    },
    {
      "type": {
        "label": "name",
        "beforeExpr": false,
        "startsExpr": true,
        "rightAssociative": false,
        "isLoop": false,
        "isAssign": false,
        "prefix": false,
        "postfix": false,
        "binop": null
      },
      "value": "broadcast",
      "start": 6,
      "end": 15,
      "loc": {
        "start": {
          "line": 1,
          "column": 6
        },
        "end": {
          "line": 1,
          "column": 15
        }
      }
    },
    {
      "type": {
        "label": "=",
        "beforeExpr": true,
        "startsExpr": false,
        "rightAssociative": false,
        "isLoop": false,
        "isAssign": true,
        "prefix": false,
        "postfix": false,
        "binop": null,
        "updateContext": null
      },
      "value": "=",
      "start": 16,
      "end": 17,
      "loc": {
        "start": {
          "line": 1,
          "column": 16
        },
        "end": {
          "line": 1,
          "column": 17
        }
      }
    },
    {
      "type": {
        "label": "name",
        "beforeExpr": false,
        "startsExpr": true,
        "rightAssociative": false,
        "isLoop": false,
        "isAssign": false,
        "prefix": false,
        "postfix": false,
        "binop": null
      },
      "value": "require",
      "start": 18,
      "end": 25,
      "loc": {
        "start": {
          "line": 1,
          "column": 18
        },
        "end": {
          "line": 1,
          "column": 25
        }
      }
    },
    {
      "type": {
        "label": "(",
        "beforeExpr": true,
        "startsExpr": true,
        "rightAssociative": false,
        "isLoop": false,
        "isAssign": false,
        "prefix": false,
        "postfix": false,
        "binop": null
      },
      "start": 25,
      "end": 26,
      "loc": {
        "start": {
          "line": 1,
          "column": 25
        },
        "end": {
          "line": 1,
          "column": 26
        }
      }
    },
    {
      "type": {
        "label": "string",
        "beforeExpr": false,
        "startsExpr": true,
        "rightAssociative": false,
        "isLoop": false,
        "isAssign": false,
        "prefix": false,
        "postfix": false,
        "binop": null,
        "updateContext": null
      },
      "value": "./broadcast.js",
      "start": 26,
      "end": 42,
      "loc": {
        "start": {
          "line": 1,
          "column": 26
        },
        "end": {
          "line": 1,
          "column": 42
        }
      }
    },
    {
      "type": {
        "label": ")",
        "beforeExpr": false,
        "startsExpr": false,
        "rightAssociative": false,
        "isLoop": false,
        "isAssign": false,
        "prefix": false,
        "postfix": false,
        "binop": null
      },
      "start": 42,
      "end": 43,
      "loc": {
        "start": {
          "line": 1,
          "column": 42
        },
        "end": {
          "line": 1,
          "column": 43
        }
      }
    },
    {
      "type": {
        "label": ";",
        "beforeExpr": true,
        "startsExpr": false,
        "rightAssociative": false,
        "isLoop": false,
        "isAssign": false,
        "prefix": false,
        "postfix": false,
        "binop": null,
        "updateContext": null
      },
      "start": 43,
      "end": 44,
      "loc": {
        "start": {
          "line": 1,
          "column": 43
        },
        "end": {
          "line": 1,
          "column": 44
        }
      }
    },
    {
      "type": {
        "label": "const",
        "keyword": "const",
        "beforeExpr": false,
        "startsExpr": false,
        "rightAssociative": false,
        "isLoop": false,
        "isAssign": false,
        "prefix": false,
        "postfix": false,
        "binop": null,
        "updateContext": null
      },
      "value": "const",
      "start": 45,
      "end": 50,
      "loc": {
        "start": {
          "line": 2,
          "column": 0
        },
        "end": {
          "line": 2,
          "column": 5
        }
      }
    },
    {
      "type": {
        "label": "name",
        "beforeExpr": false,
        "startsExpr": true,
        "rightAssociative": false,
        "isLoop": false,
        "isAssign": false,
        "prefix": false,
        "postfix": false,
        "binop": null
      },
      "value": "logPartySize",
      "start": 51,
      "end": 63,
      "loc": {
        "start": {
          "line": 2,
          "column": 6
        },
        "end": {
          "line": 2,
          "column": 18
        }
      }
    },
    {
      "type": {
        "label": "=",
        "beforeExpr": true,
        "startsExpr": false,
        "rightAssociative": false,
        "isLoop": false,
        "isAssign": true,
        "prefix": false,
        "postfix": false,
        "binop": null,
        "updateContext": null
      },
      "value": "=",
      "start": 64,
      "end": 65,
      "loc": {
        "start": {
          "line": 2,
          "column": 19
        },
        "end": {
          "line": 2,
          "column": 20
        }
      }
    },
    {
      "type": {
        "label": "name",
        "beforeExpr": false,
        "startsExpr": true,
        "rightAssociative": false,
        "isLoop": false,
        "isAssign": false,
        "prefix": false,
        "postfix": false,
        "binop": null
      },
      "value": "require",
      "start": 66,
      "end": 73,
      "loc": {
        "start": {
          "line": 2,
          "column": 21
        },
        "end": {
          "line": 2,
          "column": 28
        }
      }
    },
    {
      "type": {
        "label": "(",
        "beforeExpr": true,
        "startsExpr": true,
        "rightAssociative": false,
        "isLoop": false,
        "isAssign": false,
        "prefix": false,
        "postfix": false,
        "binop": null
      },
      "start": 73,
      "end": 74,
      "loc": {
        "start": {
          "line": 2,
          "column": 28
        },
        "end": {
          "line": 2,
          "column": 29
        }
      }
    },
    {
      "type": {
        "label": "string",
        "beforeExpr": false,
        "startsExpr": true,
        "rightAssociative": false,
        "isLoop": false,
        "isAssign": false,
        "prefix": false,
        "postfix": false,
        "binop": null,
        "updateContext": null
      },
      "value": "./logPartySize.js",
      "start": 74,
      "end": 93,
      "loc": {
        "start": {
          "line": 2,
          "column": 29
        },
        "end": {
          "line": 2,
          "column": 48
        }
      }
    },
    {
      "type": {
        "label": ")",
        "beforeExpr": false,
        "startsExpr": false,
        "rightAssociative": false,
        "isLoop": false,
        "isAssign": false,
        "prefix": false,
        "postfix": false,
        "binop": null
      },
      "start": 93,
      "end": 94,
      "loc": {
        "start": {
          "line": 2,
          "column": 48
        },
        "end": {
          "line": 2,
          "column": 49
        }
      }
    },
    {
      "type": {
        "label": ";",
        "beforeExpr": true,
        "startsExpr": false,
        "rightAssociative": false,
        "isLoop": false,
        "isAssign": false,
        "prefix": false,
        "postfix": false,
        "binop": null,
        "updateContext": null
      },
      "start": 94,
      "end": 95,
      "loc": {
        "start": {
          "line": 2,
          "column": 49
        },
        "end": {
          "line": 2,
          "column": 50
        }
      }
    },
    {
      "type": {
        "label": "function",
        "keyword": "function",
        "beforeExpr": false,
        "startsExpr": true,
        "rightAssociative": false,
        "isLoop": false,
        "isAssign": false,
        "prefix": false,
        "postfix": false,
        "binop": null
      },
      "value": "function",
      "start": 97,
      "end": 105,
      "loc": {
        "start": {
          "line": 4,
          "column": 0
        },
        "end": {
          "line": 4,
          "column": 8
        }
      }
    },
    {
      "type": {
        "label": "name",
        "beforeExpr": false,
        "startsExpr": true,
        "rightAssociative": false,
        "isLoop": false,
        "isAssign": false,
        "prefix": false,
        "postfix": false,
        "binop": null
      },
      "value": "removePlayer",
      "start": 106,
      "end": 118,
      "loc": {
        "start": {
          "line": 4,
          "column": 9
        },
        "end": {
          "line": 4,
          "column": 21
        }
      }
    },
    {
      "type": {
        "label": "(",
        "beforeExpr": true,
        "startsExpr": true,
        "rightAssociative": false,
        "isLoop": false,
        "isAssign": false,
        "prefix": false,
        "postfix": false,
        "binop": null
      },
      "start": 118,
      "end": 119,
      "loc": {
        "start": {
          "line": 4,
          "column": 21
        },
        "end": {
          "line": 4,
          "column": 22
        }
      }
    },
    {
      "type": {
        "label": "name",
        "beforeExpr": false,
        "startsExpr": true,
        "rightAssociative": false,
        "isLoop": false,
        "isAssign": false,
        "prefix": false,
        "postfix": false,
        "binop": null
      },
      "value": "connections",
      "start": 119,
      "end": 130,
      "loc": {
        "start": {
          "line": 4,
          "column": 22
        },
        "end": {
          "line": 4,
          "column": 33
        }
      }
    },
    {
      "type": {
        "label": ",",
        "beforeExpr": true,
        "startsExpr": false,
        "rightAssociative": false,
        "isLoop": false,
        "isAssign": false,
        "prefix": false,
        "postfix": false,
        "binop": null,
        "updateContext": null
      },
      "start": 130,
      "end": 131,
      "loc": {
        "start": {
          "line": 4,
          "column": 33
        },
        "end": {
          "line": 4,
          "column": 34
        }
      }
    },
    {
      "type": {
        "label": "name",
        "beforeExpr": false,
        "startsExpr": true,
        "rightAssociative": false,
        "isLoop": false,
        "isAssign": false,
        "prefix": false,
        "postfix": false,
        "binop": null
      },
      "value": "players",
      "start": 132,
      "end": 139,
      "loc": {
        "start": {
          "line": 4,
          "column": 35
        },
        "end": {
          "line": 4,
          "column": 42
        }
      }
    },
    {
      "type": {
        "label": ",",
        "beforeExpr": true,
        "startsExpr": false,
        "rightAssociative": false,
        "isLoop": false,
        "isAssign": false,
        "prefix": false,
        "postfix": false,
        "binop": null,
        "updateContext": null
      },
      "start": 139,
      "end": 140,
      "loc": {
        "start": {
          "line": 4,
          "column": 42
        },
        "end": {
          "line": 4,
          "column": 43
        }
      }
    },
    {
      "type": {
        "label": "name",
        "beforeExpr": false,
        "startsExpr": true,
        "rightAssociative": false,
        "isLoop": false,
        "isAssign": false,
        "prefix": false,
        "postfix": false,
        "binop": null
      },
      "value": "playerId",
      "start": 141,
      "end": 149,
      "loc": {
        "start": {
          "line": 4,
          "column": 44
        },
        "end": {
          "line": 4,
          "column": 52
        }
      }
    },
    {
      "type": {
        "label": ")",
        "beforeExpr": false,
        "startsExpr": false,
        "rightAssociative": false,
        "isLoop": false,
        "isAssign": false,
        "prefix": false,
        "postfix": false,
        "binop": null
      },
      "start": 149,
      "end": 150,
      "loc": {
        "start": {
          "line": 4,
          "column": 52
        },
        "end": {
          "line": 4,
          "column": 53
        }
      }
    },
    {
      "type": {
        "label": "{",
        "beforeExpr": true,
        "startsExpr": true,
        "rightAssociative": false,
        "isLoop": false,
        "isAssign": false,
        "prefix": false,
        "postfix": false,
        "binop": null
      },
      "start": 151,
      "end": 152,
      "loc": {
        "start": {
          "line": 4,
          "column": 54
        },
        "end": {
          "line": 4,
          "column": 55
        }
      }
    },
    {
      "type": {
        "label": "name",
        "beforeExpr": false,
        "startsExpr": true,
        "rightAssociative": false,
        "isLoop": false,
        "isAssign": false,
        "prefix": false,
        "postfix": false,
        "binop": null
      },
      "value": "players",
      "start": 157,
      "end": 164,
      "loc": {
        "start": {
          "line": 5,
          "column": 4
        },
        "end": {
          "line": 5,
          "column": 11
        }
      }
    },
    {
      "type": {
        "label": "[",
        "beforeExpr": true,
        "startsExpr": true,
        "rightAssociative": false,
        "isLoop": false,
        "isAssign": false,
        "prefix": false,
        "postfix": false,
        "binop": null,
        "updateContext": null
      },
      "start": 164,
      "end": 165,
      "loc": {
        "start": {
          "line": 5,
          "column": 11
        },
        "end": {
          "line": 5,
          "column": 12
        }
      }
    },
    {
      "type": {
        "label": "name",
        "beforeExpr": false,
        "startsExpr": true,
        "rightAssociative": false,
        "isLoop": false,
        "isAssign": false,
        "prefix": false,
        "postfix": false,
        "binop": null
      },
      "value": "playerId",
      "start": 165,
      "end": 173,
      "loc": {
        "start": {
          "line": 5,
          "column": 12
        },
        "end": {
          "line": 5,
          "column": 20
        }
      }
    },
    {
      "type": {
        "label": "]",
        "beforeExpr": false,
        "startsExpr": false,
        "rightAssociative": false,
        "isLoop": false,
        "isAssign": false,
        "prefix": false,
        "postfix": false,
        "binop": null,
        "updateContext": null
      },
      "start": 173,
      "end": 174,
      "loc": {
        "start": {
          "line": 5,
          "column": 20
        },
        "end": {
          "line": 5,
          "column": 21
        }
      }
    },
    {
      "type": {
        "label": "=",
        "beforeExpr": true,
        "startsExpr": false,
        "rightAssociative": false,
        "isLoop": false,
        "isAssign": true,
        "prefix": false,
        "postfix": false,
        "binop": null,
        "updateContext": null
      },
      "value": "=",
      "start": 175,
      "end": 176,
      "loc": {
        "start": {
          "line": 5,
          "column": 22
        },
        "end": {
          "line": 5,
          "column": 23
        }
      }
    },
    {
      "type": {
        "label": "{",
        "beforeExpr": true,
        "startsExpr": true,
        "rightAssociative": false,
        "isLoop": false,
        "isAssign": false,
        "prefix": false,
        "postfix": false,
        "binop": null
      },
      "start": 177,
      "end": 178,
      "loc": {
        "start": {
          "line": 5,
          "column": 24
        },
        "end": {
          "line": 5,
          "column": 25
        }
      }
    },
    {
      "type": {
        "label": "}",
        "beforeExpr": false,
        "startsExpr": false,
        "rightAssociative": false,
        "isLoop": false,
        "isAssign": false,
        "prefix": false,
        "postfix": false,
        "binop": null
      },
      "start": 178,
      "end": 179,
      "loc": {
        "start": {
          "line": 5,
          "column": 25
        },
        "end": {
          "line": 5,
          "column": 26
        }
      }
    },
    {
      "type": {
        "label": ";",
        "beforeExpr": true,
        "startsExpr": false,
        "rightAssociative": false,
        "isLoop": false,
        "isAssign": false,
        "prefix": false,
        "postfix": false,
        "binop": null,
        "updateContext": null
      },
      "start": 179,
      "end": 180,
      "loc": {
        "start": {
          "line": 5,
          "column": 26
        },
        "end": {
          "line": 5,
          "column": 27
        }
      }
    },
    {
      "type": {
        "label": "name",
        "beforeExpr": false,
        "startsExpr": true,
        "rightAssociative": false,
        "isLoop": false,
        "isAssign": false,
        "prefix": false,
        "postfix": false,
        "binop": null
      },
      "value": "broadcast",
      "start": 185,
      "end": 194,
      "loc": {
        "start": {
          "line": 6,
          "column": 4
        },
        "end": {
          "line": 6,
          "column": 13
        }
      }
    },
    {
      "type": {
        "label": "(",
        "beforeExpr": true,
        "startsExpr": true,
        "rightAssociative": false,
        "isLoop": false,
        "isAssign": false,
        "prefix": false,
        "postfix": false,
        "binop": null
      },
      "start": 194,
      "end": 195,
      "loc": {
        "start": {
          "line": 6,
          "column": 13
        },
        "end": {
          "line": 6,
          "column": 14
        }
      }
    },
    {
      "type": {
        "label": "name",
        "beforeExpr": false,
        "startsExpr": true,
        "rightAssociative": false,
        "isLoop": false,
        "isAssign": false,
        "prefix": false,
        "postfix": false,
        "binop": null
      },
      "value": "connections",
      "start": 195,
      "end": 206,
      "loc": {
        "start": {
          "line": 6,
          "column": 14
        },
        "end": {
          "line": 6,
          "column": 25
        }
      }
    },
    {
      "type": {
        "label": ",",
        "beforeExpr": true,
        "startsExpr": false,
        "rightAssociative": false,
        "isLoop": false,
        "isAssign": false,
        "prefix": false,
        "postfix": false,
        "binop": null,
        "updateContext": null
      },
      "start": 206,
      "end": 207,
      "loc": {
        "start": {
          "line": 6,
          "column": 25
        },
        "end": {
          "line": 6,
          "column": 26
        }
      }
    },
    {
      "type": {
        "label": "{",
        "beforeExpr": true,
        "startsExpr": true,
        "rightAssociative": false,
        "isLoop": false,
        "isAssign": false,
        "prefix": false,
        "postfix": false,
        "binop": null
      },
      "start": 208,
      "end": 209,
      "loc": {
        "start": {
          "line": 6,
          "column": 27
        },
        "end": {
          "line": 6,
          "column": 28
        }
      }
    },
    {
      "type": {
        "label": "name",
        "beforeExpr": false,
        "startsExpr": true,
        "rightAssociative": false,
        "isLoop": false,
        "isAssign": false,
        "prefix": false,
        "postfix": false,
        "binop": null
      },
      "value": "type",
      "start": 209,
      "end": 213,
      "loc": {
        "start": {
          "line": 6,
          "column": 28
        },
        "end": {
          "line": 6,
          "column": 32
        }
      }
    },
    {
      "type": {
        "label": ":",
        "beforeExpr": true,
        "startsExpr": false,
        "rightAssociative": false,
        "isLoop": false,
        "isAssign": false,
        "prefix": false,
        "postfix": false,
        "binop": null,
        "updateContext": null
      },
      "start": 213,
      "end": 214,
      "loc": {
        "start": {
          "line": 6,
          "column": 32
        },
        "end": {
          "line": 6,
          "column": 33
        }
      }
    },
    {
      "type": {
        "label": "string",
        "beforeExpr": false,
        "startsExpr": true,
        "rightAssociative": false,
        "isLoop": false,
        "isAssign": false,
        "prefix": false,
        "postfix": false,
        "binop": null,
        "updateContext": null
      },
      "value": "player-left",
      "start": 215,
      "end": 228,
      "loc": {
        "start": {
          "line": 6,
          "column": 34
        },
        "end": {
          "line": 6,
          "column": 47
        }
      }
    },
    {
      "type": {
        "label": ",",
        "beforeExpr": true,
        "startsExpr": false,
        "rightAssociative": false,
        "isLoop": false,
        "isAssign": false,
        "prefix": false,
        "postfix": false,
        "binop": null,
        "updateContext": null
      },
      "start": 228,
      "end": 229,
      "loc": {
        "start": {
          "line": 6,
          "column": 47
        },
        "end": {
          "line": 6,
          "column": 48
        }
      }
    },
    {
      "type": {
        "label": "name",
        "beforeExpr": false,
        "startsExpr": true,
        "rightAssociative": false,
        "isLoop": false,
        "isAssign": false,
        "prefix": false,
        "postfix": false,
        "binop": null
      },
      "value": "id",
      "start": 230,
      "end": 232,
      "loc": {
        "start": {
          "line": 6,
          "column": 49
        },
        "end": {
          "line": 6,
          "column": 51
        }
      }
    },
    {
      "type": {
        "label": ":",
        "beforeExpr": true,
        "startsExpr": false,
        "rightAssociative": false,
        "isLoop": false,
        "isAssign": false,
        "prefix": false,
        "postfix": false,
        "binop": null,
        "updateContext": null
      },
      "start": 232,
      "end": 233,
      "loc": {
        "start": {
          "line": 6,
          "column": 51
        },
        "end": {
          "line": 6,
          "column": 52
        }
      }
    },
    {
      "type": {
        "label": "name",
        "beforeExpr": false,
        "startsExpr": true,
        "rightAssociative": false,
        "isLoop": false,
        "isAssign": false,
        "prefix": false,
        "postfix": false,
        "binop": null
      },
      "value": "playerId",
      "start": 234,
      "end": 242,
      "loc": {
        "start": {
          "line": 6,
          "column": 53
        },
        "end": {
          "line": 6,
          "column": 61
        }
      }
    },
    {
      "type": {
        "label": "}",
        "beforeExpr": false,
        "startsExpr": false,
        "rightAssociative": false,
        "isLoop": false,
        "isAssign": false,
        "prefix": false,
        "postfix": false,
        "binop": null
      },
      "start": 242,
      "end": 243,
      "loc": {
        "start": {
          "line": 6,
          "column": 61
        },
        "end": {
          "line": 6,
          "column": 62
        }
      }
    },
    {
      "type": {
        "label": ")",
        "beforeExpr": false,
        "startsExpr": false,
        "rightAssociative": false,
        "isLoop": false,
        "isAssign": false,
        "prefix": false,
        "postfix": false,
        "binop": null
      },
      "start": 243,
      "end": 244,
      "loc": {
        "start": {
          "line": 6,
          "column": 62
        },
        "end": {
          "line": 6,
          "column": 63
        }
      }
    },
    {
      "type": {
        "label": ";",
        "beforeExpr": true,
        "startsExpr": false,
        "rightAssociative": false,
        "isLoop": false,
        "isAssign": false,
        "prefix": false,
        "postfix": false,
        "binop": null,
        "updateContext": null
      },
      "start": 244,
      "end": 245,
      "loc": {
        "start": {
          "line": 6,
          "column": 63
        },
        "end": {
          "line": 6,
          "column": 64
        }
      }
    },
    {
      "type": {
        "label": "name",
        "beforeExpr": false,
        "startsExpr": true,
        "rightAssociative": false,
        "isLoop": false,
        "isAssign": false,
        "prefix": false,
        "postfix": false,
        "binop": null
      },
      "value": "logPartySize",
      "start": 250,
      "end": 262,
      "loc": {
        "start": {
          "line": 7,
          "column": 4
        },
        "end": {
          "line": 7,
          "column": 16
        }
      }
    },
    {
      "type": {
        "label": "(",
        "beforeExpr": true,
        "startsExpr": true,
        "rightAssociative": false,
        "isLoop": false,
        "isAssign": false,
        "prefix": false,
        "postfix": false,
        "binop": null
      },
      "start": 262,
      "end": 263,
      "loc": {
        "start": {
          "line": 7,
          "column": 16
        },
        "end": {
          "line": 7,
          "column": 17
        }
      }
    },
    {
      "type": {
        "label": "name",
        "beforeExpr": false,
        "startsExpr": true,
        "rightAssociative": false,
        "isLoop": false,
        "isAssign": false,
        "prefix": false,
        "postfix": false,
        "binop": null
      },
      "value": "connections",
      "start": 263,
      "end": 274,
      "loc": {
        "start": {
          "line": 7,
          "column": 17
        },
        "end": {
          "line": 7,
          "column": 28
        }
      }
    },
    {
      "type": {
        "label": ")",
        "beforeExpr": false,
        "startsExpr": false,
        "rightAssociative": false,
        "isLoop": false,
        "isAssign": false,
        "prefix": false,
        "postfix": false,
        "binop": null
      },
      "start": 274,
      "end": 275,
      "loc": {
        "start": {
          "line": 7,
          "column": 28
        },
        "end": {
          "line": 7,
          "column": 29
        }
      }
    },
    {
      "type": {
        "label": ";",
        "beforeExpr": true,
        "startsExpr": false,
        "rightAssociative": false,
        "isLoop": false,
        "isAssign": false,
        "prefix": false,
        "postfix": false,
        "binop": null,
        "updateContext": null
      },
      "start": 275,
      "end": 276,
      "loc": {
        "start": {
          "line": 7,
          "column": 29
        },
        "end": {
          "line": 7,
          "column": 30
        }
      }
    },
    {
      "type": {
        "label": "}",
        "beforeExpr": false,
        "startsExpr": false,
        "rightAssociative": false,
        "isLoop": false,
        "isAssign": false,
        "prefix": false,
        "postfix": false,
        "binop": null
      },
      "start": 277,
      "end": 278,
      "loc": {
        "start": {
          "line": 8,
          "column": 0
        },
        "end": {
          "line": 8,
          "column": 1
        }
      }
    },
    {
      "type": {
        "label": "name",
        "beforeExpr": false,
        "startsExpr": true,
        "rightAssociative": false,
        "isLoop": false,
        "isAssign": false,
        "prefix": false,
        "postfix": false,
        "binop": null
      },
      "value": "module",
      "start": 280,
      "end": 286,
      "loc": {
        "start": {
          "line": 10,
          "column": 0
        },
        "end": {
          "line": 10,
          "column": 6
        }
      }
    },
    {
      "type": {
        "label": ".",
        "beforeExpr": false,
        "startsExpr": false,
        "rightAssociative": false,
        "isLoop": false,
        "isAssign": false,
        "prefix": false,
        "postfix": false,
        "binop": null,
        "updateContext": null
      },
      "start": 286,
      "end": 287,
      "loc": {
        "start": {
          "line": 10,
          "column": 6
        },
        "end": {
          "line": 10,
          "column": 7
        }
      }
    },
    {
      "type": {
        "label": "name",
        "beforeExpr": false,
        "startsExpr": true,
        "rightAssociative": false,
        "isLoop": false,
        "isAssign": false,
        "prefix": false,
        "postfix": false,
        "binop": null
      },
      "value": "exports",
      "start": 287,
      "end": 294,
      "loc": {
        "start": {
          "line": 10,
          "column": 7
        },
        "end": {
          "line": 10,
          "column": 14
        }
      }
    },
    {
      "type": {
        "label": "=",
        "beforeExpr": true,
        "startsExpr": false,
        "rightAssociative": false,
        "isLoop": false,
        "isAssign": true,
        "prefix": false,
        "postfix": false,
        "binop": null,
        "updateContext": null
      },
      "value": "=",
      "start": 295,
      "end": 296,
      "loc": {
        "start": {
          "line": 10,
          "column": 15
        },
        "end": {
          "line": 10,
          "column": 16
        }
      }
    },
    {
      "type": {
        "label": "name",
        "beforeExpr": false,
        "startsExpr": true,
        "rightAssociative": false,
        "isLoop": false,
        "isAssign": false,
        "prefix": false,
        "postfix": false,
        "binop": null
      },
      "value": "removePlayer",
      "start": 297,
      "end": 309,
      "loc": {
        "start": {
          "line": 10,
          "column": 17
        },
        "end": {
          "line": 10,
          "column": 29
        }
      }
    },
    {
      "type": {
        "label": ";",
        "beforeExpr": true,
        "startsExpr": false,
        "rightAssociative": false,
        "isLoop": false,
        "isAssign": false,
        "prefix": false,
        "postfix": false,
        "binop": null,
        "updateContext": null
      },
      "start": 309,
      "end": 310,
      "loc": {
        "start": {
          "line": 10,
          "column": 29
        },
        "end": {
          "line": 10,
          "column": 30
        }
      }
    },
    {
      "type": {
        "label": "eof",
        "beforeExpr": false,
        "startsExpr": false,
        "rightAssociative": false,
        "isLoop": false,
        "isAssign": false,
        "prefix": false,
        "postfix": false,
        "binop": null,
        "updateContext": null
      },
      "start": 311,
      "end": 311,
      "loc": {
        "start": {
          "line": 11,
          "column": 0
        },
        "end": {
          "line": 11,
          "column": 0
        }
      }
    }
  ]
}